wavetrace/__init__.py
wavetrace/cli.py
wavetrace/constants.py
wavetrace/main.py
wavetrace/utilities.py
wavetrace-4.0.3.data/data/LICENSE.txt
wavetrace-4.0.3.dist-info/LICENSE.txt
wavetrace-4.0.3.dist-info/METADATA
wavetrace-4.0.3.dist-info/WHEEL
wavetrace-4.0.3.dist-info/entry_points.txt
wavetrace-4.0.3.dist-info/top_level.txt
wavetrace-4.0.3.dist-info/RECORD
