Metadata-Version: 2.1
Name: wavetrace
Version: 4.0.3
Summary: Python 3.5 tools to produce radio signal coverage reports, mostly for New Zealand
Home-page: https://github.com/nzrs/wavetrace
Author: Alex Raichev
Author-email: UNKNOWN
License: GNU AFFERO GENERAL PUBLIC LICENSE
Requires-Dist: requests (>=2.20.0)
Requires-Dist: Shapely (>=1.6.4.post2)
Requires-Dist: click (>=7.0)
